opengemini_client/__init__.py
opengemini_client/client.py
opengemini_client/client_impl.py
opengemini_client/client_impl_test.py
opengemini_client/database_test.py
opengemini_client/models.py
opengemini_client/ping_test.py
opengemini_client/query_test.py
opengemini_client/retention_policy_test.py
opengemini_client/test_utils.py
opengemini_client/url_const.py
opengemini_client/utils.py
opengemini_client-0.0.1.dist-info/LICENSE
opengemini_client-0.0.1.dist-info/METADATA
opengemini_client-0.0.1.dist-info/WHEEL
opengemini_client-0.0.1.dist-info/top_level.txt
opengemini_client-0.0.1.dist-info/RECORD
